agentrl/worker/__init__.py
agentrl/worker/__main__.py
agentrl/worker/_version.py
agentrl/worker/py.typed
agentrl/worker/snapshots.py
agentrl/worker/task.py
agentrl/worker/task_worker.py
agentrl/worker/task_worker_grpc.py
agentrl/worker/trace_store.py
agentrl/worker/typings.py
agentrl/worker/utils.py
agentrl/worker/config/__init__.py
agentrl/worker/config/__main__.py
agentrl/worker/config/consul.py
agentrl/worker/config/loader.py
agentrl/worker/environment/__init__.py
agentrl/worker/environment/_base.py
agentrl/worker/environment/_const.py
agentrl/worker/environment/_delegation.py
agentrl/worker/environment/_typings.py
agentrl/worker/environment/docker.py
agentrl/worker/environment/k8s.py
agentrl/worker/environment/manual.py
agentrl/worker/environment/state/__init__.py
agentrl/worker/environment/state/_base.py
agentrl/worker/environment/state/consul.py
agentrl/worker/environment/state/etcd.py
agentrl/worker/environment/state/local.py
agentrl/worker/environment/state/redis.py
agentrl/worker/pb/__init__.py
agentrl/worker/pb/common_pb2.py
agentrl/worker/pb/common_pb2.pyi
agentrl/worker/pb/common_pb2_grpc.py
agentrl/worker/pb/controller_v1/__init__.py
agentrl/worker/pb/controller_v1/controller_pb2.py
agentrl/worker/pb/controller_v1/controller_pb2.pyi
agentrl/worker/pb/controller_v1/controller_pb2_grpc.py
agentrl/worker/pb/snapshots_v1/__init__.py
agentrl/worker/pb/snapshots_v1/snapshots_pb2.py
agentrl/worker/pb/snapshots_v1/snapshots_pb2.pyi
agentrl/worker/pb/snapshots_v1/snapshots_pb2_grpc.py
agentrl_worker-0.4.0.dist-info/METADATA
agentrl_worker-0.4.0.dist-info/WHEEL
agentrl_worker-0.4.0.dist-info/top_level.txt
agentrl_worker-0.4.0.dist-info/RECORD
